mcp_google_cloud_billing/__init__.py
mcp_google_cloud_billing/server.py
mcp_google_cloud_billing-0.0.3.dist-info/METADATA
mcp_google_cloud_billing-0.0.3.dist-info/WHEEL
mcp_google_cloud_billing-0.0.3.dist-info/entry_points.txt
mcp_google_cloud_billing-0.0.3.dist-info/top_level.txt
mcp_google_cloud_billing-0.0.3.dist-info/RECORD
